bushk/__init__.py
bushk/errors.py
bushk/eta.py
bushk/routes.py
bushk/stops.py
bushk-0.0.2.dist-info/LICENSE
bushk-0.0.2.dist-info/METADATA
bushk-0.0.2.dist-info/WHEEL
bushk-0.0.2.dist-info/top_level.txt
bushk-0.0.2.dist-info/RECORD
