Metadata-Version: 2.1
Name: bushk
Version: 0.0.2
Summary: 取得香港巴士的數據!
Home-page: https://github.com/max-github110331/bushk
Author: MaxPython110331
License: MIT
Classifier: Programming Language :: Python :: 3
Classifier: License :: OSI Approved :: MIT License
Classifier: Operating System :: OS Independent
Requires-Python: >=3.10
License-File: LICENSE
Requires-Dist: requests
